{
  "parent": "woot:main/ya_hammer",
  "display": {
    "icon": {
      "item": "woot:si_dust"
    },
    "title": {
      "translate": "advancements.woot.si_dust.title"
    },
    "description": {
      "translate": "advancements.woot.si_dust.description"
    },
    "frame": "task",
    "show_toast": false,
    "announce_to_chat": true,
    "hidden": false,
    "background": "minecraft:textures/block/black_concrete_powder.png"
  },
  "criteria": {
    "si_dust": {
      "trigger": "minecraft:inventory_changed",
      "conditions": {
        "items": [
          {
            "item": "woot:si_dust"
          }
        ]
      }
    }
  },
  "requirements": [
    [
      "si_dust"
    ]
  ]
}