{
  "ingredients": {
    "enchanted_book": "ipsis.woot.crafting.ingredient.EnchantedBookIngredientFactory"
  },
  "conditions": {
    "vanilla_die_crafting": "ipsis.woot.crafting.VanillaDieCraftingConditionFactory",
    "xp_upgrade": "ipsis.woot.crafting.XpUpgradeConditionFactory",
    "bm_le_tank": "ipsis.woot.crafting.BmLeTankUpgradeConditionFactory",
    "bm_le_altar": "ipsis.woot.crafting.BmLeAltarUpgradeConditionFactory",
    "ec_blood_tank": "ipsis.woot.crafting.EcBloodTankConditionFactory"
  }
}